[{
    "label": "Focus Technology",
    "entries": [{
        "order": 1,
        "headline": "Phase 0: Focused Technology",
        "content": "I have recently finished the design for the six Primal Focuses that will be located at various locations across planet Nexus.\n\nThese will be essential to completing the first phase of the Project, but I foresee other, more interesting applications for them as well.\n\nI am not one to sing my own praises, but these devices are some of the most advanced pieces of technology that the Eldan have ever created.",
        "source": "Datacube by Vorion",
        "sourcetype": "datacube"
    }]
}, {}, {}, {}, {}, {
    "label": "Element",
    "entries": [{}]
}, {
    "label": "Elementals",
    "entries": [{}]
}]
